dooray_mcp/__init__.py
dooray_mcp/cli.py
dooray_mcp/main.py
dooray_mcp/controllers/__init__.py
dooray_mcp/controllers/comment.py
dooray_mcp/controllers/task.py
dooray_mcp/services/__init__.py
dooray_mcp/services/client.py
dooray_mcp/services/comment_api.py
dooray_mcp/services/task_api.py
dooray_mcp/tools/__init__.py
dooray_mcp/tools/comment.py
dooray_mcp/tools/task.py
dooray_mcp/types/__init__.py
dooray_mcp/types/comment.py
dooray_mcp/types/common.py
dooray_mcp/types/task.py
dooray_mcp/utils/__init__.py
dooray_mcp/utils/config.py
dooray_mcp/utils/errors.py
dooray_mcp/utils/logger.py
dooray_mcp-0.1.2.dist-info/METADATA
dooray_mcp-0.1.2.dist-info/WHEEL
dooray_mcp-0.1.2.dist-info/entry_points.txt
dooray_mcp-0.1.2.dist-info/RECORD
