Metadata-Version: 2.4
Name: dooray-mcp
Version: 0.1.2
Summary: MCP server for Dooray task and calendar integration
Project-URL: Homepage, https://github.com/kwanok/dooray-mcp
Project-URL: Repository, https://github.com/kwanok/dooray-mcp
Project-URL: Issues, https://github.com/kwanok/dooray-mcp/issues
Requires-Python: >=3.11
Requires-Dist: httpx>=0.27.0
Requires-Dist: mcp>=1.0.0
Requires-Dist: pydantic>=2.0.0
Requires-Dist: python-dotenv>=1.0.0
Requires-Dist: rich>=13.0.0
Requires-Dist: typer>=0.12.0
Provides-Extra: dev
Requires-Dist: pytest-asyncio>=0.23.0; extra == 'dev'
Requires-Dist: pytest>=8.0.0; extra == 'dev'
Requires-Dist: ruff>=0.4.0; extra == 'dev'
